spreadsheet_mcp/__init__.py
spreadsheet_mcp/cli.py
spreadsheet_mcp/server.py
spreadsheet_mcp/sheet.py
spreadsheet_mcp-0.1.0.dist-info/METADATA
spreadsheet_mcp-0.1.0.dist-info/WHEEL
spreadsheet_mcp-0.1.0.dist-info/entry_points.txt
spreadsheet_mcp-0.1.0.dist-info/RECORD
