Metadata-Version: 2.4
Name: spreadsheet-mcp
Version: 0.1.0
Summary: Google Spreadsheetを操作するためのMCPサーバー
Requires-Python: >=3.11
Requires-Dist: gspread>=6.2.0
Requires-Dist: mcp[cli]>=1.6.0
Requires-Dist: polars>=1.26.0
